setup.py
warnings.py
micropython_warnings.egg-info/PKG-INFO
micropython_warnings.egg-info/SOURCES.txt
micropython_warnings.egg-info/dependency_links.txt
micropython_warnings.egg-info/top_level.txt